LICENSE
MANIFEST.in
setup.cfg
setup.py
archipel_agent_virtualmachine_vnc.egg-info/PKG-INFO
archipel_agent_virtualmachine_vnc.egg-info/SOURCES.txt
archipel_agent_virtualmachine_vnc.egg-info/dependency_links.txt
archipel_agent_virtualmachine_vnc.egg-info/entry_points.txt
archipel_agent_virtualmachine_vnc.egg-info/not-zip-safe
archipel_agent_virtualmachine_vnc.egg-info/requires.txt
archipel_agent_virtualmachine_vnc.egg-info/top_level.txt
archipelagentvirtualmachinevnc/__init__.py
archipelagentvirtualmachinevnc/__init__.pyc
archipelagentvirtualmachinevnc/archipelWebSocket.pyc
archipelagentvirtualmachinevnc/vnc.py
archipelagentvirtualmachinevnc/vnc.pyc
archipelagentvirtualmachinevnc/websocket.py
archipelagentvirtualmachinevnc/websocket.pyc
archipelagentvirtualmachinevnc/websockify.py
archipelagentvirtualmachinevnc/websockify.pyc